card_trick/__init__.py
card_trick/commands.py
card_trick/ontology_functions.py
card_trick-0.2.1.data/scripts/card-trick
card_trick-0.2.1.dist-info/LICENSE
card_trick-0.2.1.dist-info/METADATA
card_trick-0.2.1.dist-info/WHEEL
card_trick-0.2.1.dist-info/top_level.txt
card_trick-0.2.1.dist-info/RECORD
