Metadata-Version: 2.1
Name: card-trick
Version: 0.2.1
Summary: Utility package to find gene - drug relationships within CARD
Home-page: UNKNOWN
Author: Anthony Underwood
Author-email: au3@sanger.ac.uk
License: MIT
Platform: UNKNOWN
Classifier: Development Status :: 3 - Alpha
Classifier: Intended Audience :: Science/Research
Classifier: License :: OSI Approved :: MIT License
Classifier: Programming Language :: Python :: 3
Requires-Dist: pronto (>=2.2)
Requires-Dist: requests
